faker_sqlalchemy.py
faker_sqlalchemy-0.10.2208140.dist-info/LICENSE
faker_sqlalchemy-0.10.2208140.dist-info/WHEEL
faker_sqlalchemy-0.10.2208140.dist-info/METADATA
faker_sqlalchemy-0.10.2208140.dist-info/RECORD
