Metadata-Version: 2.1
Name: faker_sqlalchemy
Version: 0.10.2208140
Summary: A Faker provider that generates data based on SQL Alchemy column types.
Author-email: The Magnificant Nick <send-me-spam@yahoo.com>
Requires-Python: >=3.7
Classifier: Development Status :: 4 - Beta
Classifier: Intended Audience :: Developers
Classifier: License :: OSI Approved :: MIT License
Classifier: Programming Language :: Python
Classifier: Programming Language :: Python :: 3
Classifier: Programming Language :: Python :: 3.7
Classifier: Programming Language :: Python :: 3.8
Classifier: Programming Language :: Python :: 3.9
Classifier: Programming Language :: Python :: 3.10
Classifier: Topic :: Software Development
Classifier: Topic :: Software Development :: Build Tools
Classifier: Topic :: Software Development :: Libraries
Classifier: Topic :: Software Development :: Testing
Classifier: Topic :: Software Development :: Testing :: Unit
Classifier: Topic :: Software Development :: Testing :: Mocking
Classifier: Topic :: Utilities
Requires-Dist: faker >=8.0
Requires-Dist: sqlalchemy >=1.3,<2.0
Requires-Dist: sphinx ; extra == "doc"
Requires-Dist: sphinx-rtd-theme ; extra == "doc"
Requires-Dist: tox-gh-actions ; extra == "github"
Requires-Dist: black ; extra == "test"
Requires-Dist: tox >=4.0.b2 ; extra == "test"
Project-URL: Documentation, https://faker-sqlalchemy.readthedocs.io/en/latest/
Project-URL: Homepage, https://github.com/nickswebsite/faker-sqlalchemy
Project-URL: Source, https://github.com/nickswebsite/faker-sqlalchemy
Provides-Extra: doc
Provides-Extra: github
Provides-Extra: test
